CHANGES.md
MANIFEST.in
README.md
setup.py
django_terra_utils.egg-info/PKG-INFO
django_terra_utils.egg-info/SOURCES.txt
django_terra_utils.egg-info/dependency_links.txt
django_terra_utils.egg-info/requires.txt
django_terra_utils.egg-info/top_level.txt
terra_utils/VERSION.md
terra_utils/__init__.py
terra_utils/apps.py
terra_utils/filters.py
terra_utils/mixins.py
terra_utils/pagination.py
terra_utils/settings.py
terra_utils/urls.py
terra_utils/views.py
terra_utils/helpers/__init__.py
terra_utils/helpers/responses.py
terra_utils/management/__init__.py
terra_utils/management/commands/__init__.py
terra_utils/management/commands/populatedata.py
terra_utils/templatetags/__init__.py
terra_utils/templatetags/settings_tags.py
terra_utils/tests/__init__.py
terra_utils/tests/test_commands.py
terra_utils/tests/test_filters.py
terra_utils/tests/test_helpers.py
terra_utils/tests/test_templatetags.py
terra_utils/tests/test_views.py
terra_utils/tests/test_app/__init__.py
terra_utils/tests/test_app/models.py
terra_utils/tests/test_app/serializers.py
terra_utils/tests/test_app/views.py
terra_utils/tests/test_app/migrations/0001_initial.py
terra_utils/tests/test_app/migrations/__init__.py